LICENSE
MANIFEST.in
README.rst
pyproject.toml
setup.py
django_epic.egg-info/PKG-INFO
django_epic.egg-info/SOURCES.txt
django_epic.egg-info/dependency_links.txt
django_epic.egg-info/requires.txt
django_epic.egg-info/top_level.txt
epic/__init__.py
epic/admin.py
epic/apps.py
epic/base.py
epic/exports.py
epic/footprints.py
epic/imports.py
epic/lib.py
epic/models.py
epic/perms.py
epic/signals.py
epic/stock_cache.py
epic/tests.py
epic/urls.py
epic/views.py
epic/widgets.py
epic/api/__init__.py
epic/api/urls.py
epic/api/views.py
epic/kicad/__init__.py
epic/kicad/bom.py
epic/kicad/csv.py
epic/kicad/epic_client.py
epic/kicad/error.py
epic/kicad/parts_cache.py
epic/kicad/schematics.py
epic/kicad/scripts.py
epic/kicad/vendors_cache.py
epic/migrations/0001_initial.py
epic/migrations/0002_auto_20150128_2344.py
epic/migrations/0003_auto_20150915_1436.py
epic/migrations/0004_auto_20150918_2111.py
epic/migrations/0005_alter_datasheet_ds_file.py
epic/migrations/0006_auto_20170509_0422.py
epic/migrations/0007_auto_20170510_0436.py
epic/migrations/0008_auto_20180203_0553.py
epic/migrations/0009_auto_20191003_2243.py
epic/migrations/0010_auto_20211108_1718.py
epic/migrations/0011_auto_20220725_0413.py
epic/migrations/0012_alter_part_footprint.py
epic/migrations/0013_rename_assembly_item_assy_comp_epic_assemb_assy_id_dcc6cf_idx_and_more.py
epic/migrations/__init__.py
epic/migrations/__init__.pyc
epic/migrations/__pycache__/0001_initial.cpython-312.pyc
epic/migrations/__pycache__/0002_auto_20150128_2344.cpython-312.pyc
epic/migrations/__pycache__/0003_auto_20150915_1436.cpython-312.pyc
epic/migrations/__pycache__/0004_auto_20150918_2111.cpython-312.pyc
epic/migrations/__pycache__/0005_alter_datasheet_ds_file.cpython-312.pyc
epic/migrations/__pycache__/0006_auto_20170509_0422.cpython-312.pyc
epic/migrations/__pycache__/0007_auto_20170510_0436.cpython-312.pyc
epic/migrations/__pycache__/0008_auto_20180203_0553.cpython-312.pyc
epic/migrations/__pycache__/0009_auto_20191003_2243.cpython-312.pyc
epic/migrations/__pycache__/0010_auto_20211108_1718.cpython-312.pyc
epic/migrations/__pycache__/0011_auto_20220725_0413.cpython-312.pyc
