Metadata-Version: 2.4
Name: django-epic
Version: 0.6.10
Summary: A Django app to manage electronic parts inventories for PCB manufacturing.
Home-page: https://bitbucket.org/egauge/epic/
Author: David Mosberger-Tang
Author-email: davidm@egauge.net
License: MIT License
Classifier: Development Status :: 4 - Beta
Classifier: Environment :: Web Environment
Classifier: Framework :: Django
Classifier: Intended Audience :: Manufacturing
Classifier: License :: OSI Approved :: MIT License
Classifier: Operating System :: OS Independent
Classifier: Programming Language :: Python
Classifier: Programming Language :: Python :: 3
Classifier: Programming Language :: Python :: 3.12
Classifier: Topic :: Scientific/Engineering :: Electronic Design Automation (EDA)
License-File: LICENSE
Requires-Dist: egauge-python>=0.9.8
Requires-Dist: sexpdata
Provides-Extra: server
Requires-Dist: django>=2.0.0; extra == "server"
Requires-Dist: django-autocomplete-light>=3; extra == "server"
Requires-Dist: django-bootstrap3-datetimepicker-2; extra == "server"
Requires-Dist: django-crispy-forms; extra == "server"
Requires-Dist: django-filter; extra == "server"
Requires-Dist: djangorestframework; extra == "server"
Requires-Dist: openpyxl; extra == "server"
Requires-Dist: tablib>=3.0.0; extra == "server"
Dynamic: author
Dynamic: author-email
Dynamic: classifier
Dynamic: description
Dynamic: home-page
Dynamic: license
Dynamic: license-file
Dynamic: provides-extra
Dynamic: requires-dist
Dynamic: summary
